reed_solomon_ccsds/__init__.py
reed_solomon_ccsds/py.typed
reed_solomon_ccsds/reed_solomon.py
reed_solomon_ccsds-1.0.3.dist-info/METADATA
reed_solomon_ccsds-1.0.3.dist-info/WHEEL
reed_solomon_ccsds-1.0.3.dist-info/licenses/LICENSE
reed_solomon_ccsds-1.0.3.dist-info/RECORD
